talky/__init__.py
talky/autostart.py
talky/main.py
talky/version.py
talky/audio/__init__.py
talky/audio/base.py
talky/audio/capture.py
talky/hotkeys/__init__.py
talky/hotkeys/base.py
talky/hotkeys/factory.py
talky/hotkeys/wayland.py
talky/hotkeys/x11.py
talky/input/__init__.py
talky/input/base.py
talky/input/factory.py
talky/input/wayland.py
talky/input/x11.py
talky/ui/__init__.py
talky/ui/icons.py
talky/ui/notifications.py
talky/ui/settings.py
talky/ui/setup_wizard.py
talky/ui/tray.py
talky/ui/wayland_setup.py
talky/utils/__init__.py
talky/utils/config.py
talky/utils/platform.py
talky/whisper/__init__.py
talky/whisper/base.py
talky/whisper/factory.py
talky/whisper/faster_whisper_engine.py
talky/whisper/languages.py
talky_dictation-0.5.0.dist-info/METADATA
talky_dictation-0.5.0.dist-info/WHEEL
talky_dictation-0.5.0.dist-info/entry_points.txt
talky_dictation-0.5.0.dist-info/top_level.txt
talky_dictation-0.5.0.dist-info/RECORD
