Metadata-Version: 2.4
Name: talky-dictation
Version: 0.5.0
Summary: System-wide dictation for Linux using OpenAI's Whisper AI
Author-email: Talky Contributors <talky@example.com>
Maintainer-email: Talky Contributors <talky@example.com>
License: MIT
Project-URL: Homepage, https://github.com/ChrisKalahiki/talky
Project-URL: Documentation, https://github.com/ChrisKalahiki/talky#readme
Project-URL: Repository, https://github.com/ChrisKalahiki/talky
Project-URL: Bug Tracker, https://github.com/ChrisKalahiki/talky/issues
Project-URL: Changelog, https://github.com/ChrisKalahiki/talky/blob/main/CHANGELOG.md
Keywords: dictation,speech-to-text,whisper,voice-typing,speech-recognition,linux,accessibility,voice-control
Classifier: Development Status :: 4 - Beta
Classifier: Intended Audience :: End Users/Desktop
Classifier: Topic :: Multimedia :: Sound/Audio :: Speech
Classifier: Topic :: Desktop Environment
Classifier: Topic :: Adaptive Technologies
Classifier: License :: OSI Approved :: MIT License
Classifier: Operating System :: POSIX :: Linux
Classifier: Programming Language :: Python :: 3
Classifier: Programming Language :: Python :: 3.10
Classifier: Programming Language :: Python :: 3.11
Classifier: Programming Language :: Python :: 3.12
Classifier: Programming Language :: Python :: 3 :: Only
Classifier: Environment :: X11 Applications
Classifier: Natural Language :: English
Requires-Python: >=3.10
Requires-Dist: faster-whisper>=1.0.0
Requires-Dist: numpy>=1.24.0
Requires-Dist: sounddevice>=0.4.6
Requires-Dist: pystray>=0.19.5
Requires-Dist: Pillow>=10.0.0
Requires-Dist: pynput>=1.7.6
Requires-Dist: notify2>=0.3.1
Requires-Dist: PyYAML>=6.0.1
Requires-Dist: python-dotenv>=1.0.0
Provides-Extra: gpu
Requires-Dist: torch>=2.0.0; extra == "gpu"
Provides-Extra: dev
Requires-Dist: pytest>=7.0.0; extra == "dev"
Requires-Dist: pytest-cov>=4.0.0; extra == "dev"
Requires-Dist: black>=23.0.0; extra == "dev"
Requires-Dist: mypy>=1.0.0; extra == "dev"
Requires-Dist: ruff>=0.1.0; extra == "dev"
Provides-Extra: test
Requires-Dist: pytest>=7.0.0; extra == "test"
Requires-Dist: psutil>=5.9.0; extra == "test"
